lib_hck/__init__.py
lib_hck/data/Heecking_tutorials.pdf
lib_hck/data/P10.csv
lib_hck/data/P2.csv
lib_hck/data/names.png
lib_hck-0.1.dist-info/METADATA
lib_hck-0.1.dist-info/WHEEL
lib_hck-0.1.dist-info/top_level.txt
lib_hck-0.1.dist-info/RECORD
